{
  "type": "FeatureCollection",
  "name": "Delhi_OFM_Distribution",
  "location": "Red Distribution",
  "crs": {
    "type": "name",
    "properties": { "name": "urn:ogc:def:crs:OGC:1.3:CRS84" }
  },

  "features": [
    {
      "type": "Feature",
      "networkDistribition": "Red Distribution",
      "icon": "assets/images/distribution-box-red.svg",
      "color": "#ff0000",
      "rotation": 90,
      "properties": { "name": "A" },
      "geometry": {
        "type": "Point",
        "coordinates": [77.174709, 28.642133]
      }
    },
    {
      "type": "Feature",
      "networkDistribition": "Red Distribution",
      "icon": "assets/images/distribution-box-red.svg",
      "color": "#ff0000",
      "rotation": 90,
      "properties": { "name": "B" },
      "geometry": {
        "type": "Point",
        "coordinates": [77.188785, 28.650436]
      }
    },
    {
      "type": "Feature",
      "networkDistribition": "Red Distribution",
      "icon": "assets/images/distribution-box-red.svg",
      "color": "#ff0000",
      "rotation": 90,
      "properties": { "name": "C" },
      "geometry": {
        "type": "Point",
        "coordinates": [77.19706, 28.645535]
      }
    },
    {
      "type": "Feature",
      "networkDistribition": "Red Distribution",
      "icon": "assets/images/distribution-box-red.svg",
      "color": "#ff0000",
      "rotation": 90,
      "properties": { "name": "D" },
      "geometry": {
        "type": "Point",
        "coordinates": [77.153235, 28.649955]
      }
    },
    {
      "type": "Feature",
      "networkDistribition": "Red Distribution",
      "icon": "assets/images/distribution-box-red.svg",
      "color": "#ff0000",
      "rotation": 90,
      "properties": { "name": "E" },
      "geometry": {
        "type": "Point",
        "coordinates": [77.18934, 28.568703]
      }
    },
    {
      "type": "Feature",
      "networkDistribition": "Red Distribution",
      "icon": "assets/images/distribution-box-red.svg",
      "color": "#ff0000",
      "rotation": 90,
      "properties": { "name": "F" },
      "geometry": {
        "type": "Point",
        "coordinates": [77.223763, 28.590513]
      }
    }
  ]
}
